ese_parser-0.1.6.dist-info/METADATA
ese_parser-0.1.6.dist-info/WHEEL
ese_parser/__init__.py
ese_parser/ese_parser.cp310-win_amd64.pyd
ese_parser-0.1.6.dist-info/RECORD
