Metadata-Version: 2.4
Name: ese-parser
Version: 0.1.6
Summary: High-performance Microsoft ESE (Extensible Storage Engine) database parser
Keywords: ese,database,parser,forensics,edb
Author: Claude Sonnet 4.5 (LOL no way im doin this by myself)
License: MIT OR Apache-2.0
Project-URL: Documentation, https://docs.rs/ese-parser
Project-URL: Source Code, https://github.com/ac-rn/ese-rs
